journal_to_fedora_messaging/__init__.py
journal_to_fedora_messaging/cli.py
journal_to_fedora_messaging/journal.py
journal_to_fedora_messaging/sender.py
journal_to_fedora_messaging-1.0.0.dist-info/LICENSES/GPL-3.0-or-later.txt
journal_to_fedora_messaging-1.0.0.dist-info/METADATA
journal_to_fedora_messaging-1.0.0.dist-info/WHEEL
journal_to_fedora_messaging-1.0.0.dist-info/entry_points.txt
journal_to_fedora_messaging-1.0.0.dist-info/RECORD
